deputil/__init__.py
deputil/__main__.py
deputil/cli.py
deputil/errors.py
deputil/types.py
deputil/api/__init__.py
deputil/api/check.py
deputil/api/deps.py
deputil/api/range.py
deputil/api/scan.py
deputil/api/versioneer.py
deputil-0.2.0.dist-info/LICENSE
deputil-0.2.0.dist-info/METADATA
deputil-0.2.0.dist-info/WHEEL
deputil-0.2.0.dist-info/entry_points.txt
deputil-0.2.0.dist-info/top_level.txt
deputil-0.2.0.dist-info/RECORD
