Metadata-Version: 2.1
Name: deputil
Version: 0.2.0
Summary: A lightweight dependency manager for Python.
Home-page: https://github.com/parafoxia/deputil
Author: Ethan Henderson
Author-email: 
License: BSD 3-Clause 'New' or 'Revised' License
Project-URL: Source, https://github.com/parafoxia/deputil
Project-URL: Bug Tracker, https://github.com/parafoxia/deputil/issues
Project-URL: CI, https://github.com/parafoxia/deputil/actions
Project-URL: Changelog, https://github.com/parafoxia/deputil/releases
Platform: UNKNOWN
Classifier: Development Status :: 3 - Alpha
Classifier: Environment :: Console
Classifier: Intended Audience :: Developers
Classifier: License :: OSI Approved :: BSD License
Classifier: Natural Language :: English
Classifier: Operating System :: MacOS
Classifier: Operating System :: Microsoft :: Windows
Classifier: Operating System :: OS Independent
Classifier: Operating System :: POSIX
Classifier: Operating System :: Unix
Classifier: Programming Language :: Python :: 3
Classifier: Programming Language :: Python :: 3 :: Only
Classifier: Programming Language :: Python :: 3.7
Classifier: Programming Language :: Python :: 3.8
Classifier: Programming Language :: Python :: 3.9
Classifier: Programming Language :: Python :: 3.10
Classifier: Programming Language :: Python :: 3.11
Classifier: Programming Language :: Python :: Implementation :: CPython
Classifier: Programming Language :: Python :: Implementation :: PyPy
Classifier: Topic :: Software Development
Classifier: Topic :: Software Development :: Quality Assurance
Classifier: Topic :: Software Development :: Version Control
Classifier: Topic :: Utilities
Classifier: Typing :: Typed
Requires-Python: >=3.7.0,<3.12
License-File: LICENSE
Requires-Dist: click (<9.0,>=8.0)
Requires-Dist: packaging (>=21.3)
Requires-Dist: pathspec (~=0.9.0)
Requires-Dist: requests (<3.0,>=2.0)
